processview/__init__.py
processview/version.py
processview/core/__init__.py
processview/core/dataset.py
processview/core/helpers.py
processview/core/setup.py
processview/core/sorting.py
processview/core/superviseprocess.py
processview/core/manager/__init__.py
processview/core/manager/manager.py
processview/core/manager/test/__init__.py
processview/core/manager/test/test_manager.py
processview/core/test/__init__.py
processview/gui/DropDownWidget.py
processview/gui/__init__.py
processview/gui/messagebox.py
processview/gui/processmanager.py
processview/gui/processmanager/ObservationTable.py
processview/gui/processmanager/ProcessManager.py
processview/gui/processmanager/ProcessManagerWidget.py
processview/gui/processmanager/ProcessManagerWindow.py
processview/gui/processmanager/_DatasetProcessModel.py
processview/gui/processmanager/_FilterWidget.py
processview/gui/processmanager/_OptionsWidget.py
processview/gui/processmanager/_OrderingWidget.py
processview/gui/processmanager/__init__.py
processview/gui/test/__init__.py
processview/gui/test/test_process_manager.py
processview/gui/utils/__init__.py
processview/gui/utils/qitem_model_resetter.py
processview/resources/__init__.py
processview/resources/gui/__init__.py
processview/resources/gui/icons/advancement.png
processview/resources/gui/icons/advancement.svg
processview/resources/gui/icons/magnifying_glass.png
processview/resources/gui/icons/magnifying_glass.svg
processview/test/__init__.py
processview/utils/__init__.py
processview/utils/singleton.py
processview-1.5.2.dist-info/licenses/LICENSE
processview-1.5.2.dist-info/METADATA
processview-1.5.2.dist-info/WHEEL
processview-1.5.2.dist-info/top_level.txt
processview-1.5.2.dist-info/zip-safe
processview-1.5.2.dist-info/RECORD
