Metadata-Version: 2.4
Name: processview
Version: 1.5.2
Summary: Simple helper to provide user feedback about dataset processing
Author: data analysis unit
Author-email: henri.payno@esrf.fr
License: MIT
Classifier: Development Status :: 5 - Production/Stable
Classifier: Environment :: Console
Classifier: Environment :: MacOS X
Classifier: Environment :: Win32 (MS Windows)
Classifier: Environment :: X11 Applications :: Qt
Classifier: Intended Audience :: Education
Classifier: Intended Audience :: Science/Research
Classifier: License :: OSI Approved :: MIT License
Classifier: Natural Language :: English
Classifier: Operating System :: MacOS
Classifier: Operating System :: Microsoft :: Windows
Classifier: Operating System :: POSIX
Classifier: Programming Language :: Cython
Classifier: Programming Language :: Python :: 3
Classifier: Topic :: Scientific/Engineering :: Physics
Classifier: Topic :: Software Development :: Libraries :: Python Modules
Requires-Python: >=3.6
License-File: LICENSE
Requires-Dist: setuptools
Requires-Dist: packaging
Requires-Dist: wheel
Requires-Dist: silx>=1.0
Provides-Extra: test
Requires-Dist: pytest; extra == "test"
Provides-Extra: doc
Requires-Dist: Sphinx; extra == "doc"
Provides-Extra: full
Requires-Dist: Sphinx; extra == "full"
Requires-Dist: pytest; extra == "full"
Requires-Dist: PyQt5; extra == "full"
Dynamic: license-file
